__init__.py
mechanics_test.py
aleatorio/__init__.py
aleatorio/aleatorio.py
matematica/__init__.py
matematica/matematica.py
pegasenha/__init__.py
pegasenha/pegasenha.py
portugython/__init__.py
portugython/embutidos.py
portugython-0.0.14.dist-info/LICENSE
portugython-0.0.14.dist-info/METADATA
portugython-0.0.14.dist-info/WHEEL
portugython-0.0.14.dist-info/top_level.txt
portugython-0.0.14.dist-info/RECORD
