Metadata-Version: 2.1
Name: portugython
Version: 0.0.14
Summary: A Portuguese translation of the Python functions/modules/packages
Author-email: Victor Kolis <victorkolis@protonmail.com>
Maintainer-email: Victor Kolis <victorkolis@protonmail.com>
Project-URL: Homepage, https://github.com/InGnave/portugython
Project-URL: Bug Tracker, https://github.com/pypa/portugython/issues
Classifier: Programming Language :: Python :: 3
Classifier: License :: OSI Approved :: MIT License
Classifier: Operating System :: OS Independent
Requires-Python: >=3.10
License-File: LICENSE
